piecrust_hoedown.py
PieCrust_Hoedown-0.1.0.dist-info/DESCRIPTION.rst
PieCrust_Hoedown-0.1.0.dist-info/METADATA
PieCrust_Hoedown-0.1.0.dist-info/RECORD
PieCrust_Hoedown-0.1.0.dist-info/WHEEL
PieCrust_Hoedown-0.1.0.dist-info/metadata.json
PieCrust_Hoedown-0.1.0.dist-info/top_level.txt
