Metadata-Version: 2.0
Name: PieCrust-Hoedown
Version: 0.1.0
Summary: Hoedown Markdown formatter for PieCrust via Misaka
Home-page: http://bolt80.com/piecrust
Author: Ludovic Chabant
Author-email: ludovic@chabant.com
License: Apache2
Platform: UNKNOWN
Classifier: Development Status :: 3 - Alpha
Classifier: Environment :: Console
Classifier: Intended Audience :: Developers
Classifier: License :: OSI Approved :: Apache Software License
Classifier: Natural Language :: English
Classifier: Operating System :: MacOS :: MacOS X
Classifier: Operating System :: POSIX :: Linux
Classifier: Operating System :: Microsoft :: Windows
Classifier: Programming Language :: Python
Classifier: Programming Language :: Python :: 3
Requires-Dist: PieCrust (>=2.0.0)
Requires-Dist: misaka (>=2.1.0)
